[
  {
    "State": "andhra-pradesh",
    "Current_Price": 1600.0,
    "Minimum_Price": 1100.0,
    "Maximum_Price": 2200.0
  },
  {
    "State": "arunachal-pradesh",
    "Current_Price": 0,
    "Minimum_Price": 0,
    "Maximum_Price": 0
  },
  {
    "State": "assam",
    "Current_Price": 1150.0,
    "Minimum_Price": 1000.0,
    "Maximum_Price": 1175.0
  },
  {
    "State": "bihar",
    "Current_Price": 1594.33,
    "Minimum_Price": 1266.67,
    "Maximum_Price": 1872.33
  },
  {
    "State": "chattisgarh",
    "Current_Price": 1466.67,
    "Minimum_Price": 1333.33,
    "Maximum_Price": 1811.0
  },
  {
    "State": "delhi",
    "Current_Price": 0,
    "Minimum_Price": 0,
    "Maximum_Price": 0
  },
  {
    "State": "gujarat",
    "Current_Price": 1395.87,
    "Minimum_Price": 853.41,
    "Maximum_Price": 2007.48
  },
  {
    "State": "haryana",
    "Current_Price": 1174.54,
    "Minimum_Price": 926.22,
    "Maximum_Price": 2098.89
  },
  {
    "State": "himachal-pradesh",
    "Current_Price": 1651.43,
    "Minimum_Price": 1077.5,
    "Maximum_Price": 2094.09
  },
  {
    "State": "jharkhand",
    "Current_Price": 0,
    "Minimum_Price": 0,
    "Maximum_Price": 0
  },
  {
    "State": "karnataka",
    "Current_Price": 2207.0,
    "Minimum_Price": 1965.33,
    "Maximum_Price": 2587.67
  },
  {
    "State": "kerala",
    "Current_Price": 3456.17,
    "Minimum_Price": 2783.33,
    "Maximum_Price": 4155.44
  },
  {
    "State": "madhya-pradesh",
    "Current_Price": 1250.0,
    "Minimum_Price": 1036.61,
    "Maximum_Price": 1745.11
  },
  {
    "State": "maharashtra",
    "Current_Price": 1677.89,
    "Minimum_Price": 1273.96,
    "Maximum_Price": 2149.3
  },
  {
    "State": "manipur",
    "Current_Price": 2750.0,
    "Minimum_Price": 2500.0,
    "Maximum_Price": 3000.0
  },
  {
    "State": "meghalaya",
    "Current_Price": 1550.0,
    "Minimum_Price": 1500.0,
    "Maximum_Price": 1600.0
  },
  {
    "State": "mizoram",
    "Current_Price": 0,
    "Minimum_Price": 0,
    "Maximum_Price": 0
  },
  {
    "State": "nagaland",
    "Current_Price": 4100.0,
    "Minimum_Price": 4000.0,
    "Maximum_Price": 4200.0
  },
  {
    "State": "odisha",
    "Current_Price": 1810.4,
    "Minimum_Price": 1439.29,
    "Maximum_Price": 2203.29
  },
  {
    "State": "punjab",
    "Current_Price": 1057.84,
    "Minimum_Price": 772.25,
    "Maximum_Price": 1405.22
  },
  {
    "State": "rajasthan",
    "Current_Price": 1212.15,
    "Minimum_Price": 1100.0,
    "Maximum_Price": 1708.37
  },
  {
    "State": "sikkim",
    "Current_Price": 0,
    "Minimum_Price": 0,
    "Maximum_Price": 0
  },
  {
    "State": "tamil-nadu",
    "Current_Price": 4061.05,
    "Minimum_Price": 3010.47,
    "Maximum_Price": 3990.53
  },
  {
    "State": "telangana",
    "Current_Price": 2966.78,
    "Minimum_Price": 2622.11,
    "Maximum_Price": 3466.67
  },
  {
    "State": "tripura",
    "Current_Price": 2151.38,
    "Minimum_Price": 1827.67,
    "Maximum_Price": 2575.33
  },
  {
    "State": "uttar-pradesh",
    "Current_Price": 1188.11,
    "Minimum_Price": 943.23,
    "Maximum_Price": 1441.06
  },
  {
    "State": "uttrakhand",
    "Current_Price": 1163.98,
    "Minimum_Price": 825.0,
    "Maximum_Price": 1479.17
  },
  {
    "State": "west-bengal",
    "Current_Price": 1321.71,
    "Minimum_Price": 1194.71,
    "Maximum_Price": 1603.6
  }
]